{
  "name": "Cindy - Comportementaliste félin",
  "shortName": "Cindy Comportementaliste félin",
  "tagline": "Comportementaliste félin diplômée",
  "url": "https://cindy-comportement-chat.fr",
  "description": "Cindy, comportementaliste félin diplômée à Castelnau-le-Lez (34). Consultations à domicile ou en visioconférence partout en France, et service de cat-sitting.",
  "email": "cindy.comportementchat@gmail.com",
  "phone": "06 09 97 00 20",
  "address": "34170 Castelnau-le-Lez, France",
  "city": "Castelnau-le-Lez",
  "region": "Occitanie",
  "postalCode": "34170",
  "geo": { "lat": "43.6341124", "lng": "3.9026777" },
  "formNextUrl": "https://cindy-comportement-chat.fr/merci/",
  "ctaLabel": "Prendre rendez-vous",
  "pageSignature": "Votre chat est unique, comme vous",
  "social": {
    "instagram": "",
    "facebook": ""
  },
  "usps": [
    { "icon": "fa-graduation-cap", "title": "Diplômée et formée", "text": "Une approche fondée sur l'éthologie féline et des formations actualisées." },
    { "icon": "fa-heart", "title": "Bienveillante, sans jugement", "text": "Un accompagnement adapté à votre chat, à vous et à votre quotidien." },
    { "icon": "fa-location-dot", "title": "À domicile ou en visio", "text": "Autour de Montpellier à domicile, où que vous soyez en visioconférence." },
    { "icon": "fa-clock-rotate-left", "title": "Suivi 3 mois / compte-rendu inclus", "text": "On ajuste ensemble les recommandations jusqu'à voir des résultats." }
  ],
  "process": [
    { "step": "1", "title": "Vous me contactez", "text": "Vous décrivez votre situation via le formulaire. Je vous recontacte rapidement pour convenir d'un rendez-vous." },
    { "step": "2", "title": "Anamnèse & entretien", "text": "Vous remplissez un questionnaire détaillé, puis nous échangeons 1h à 1h30 pour comprendre l'origine du comportement." },
    { "step": "3", "title": "Recommandations sur-mesure", "text": "Je vous remets des solutions concrètes et adaptées à votre chat et à votre mode de vie." },
    { "step": "4", "title": "Suivi 3 mois / compte-rendu inclus", "text": "Je reste à vos côtés pour ajuster les conseils et avancer vers une cohabitation sereine." }
  ],
  "zones": [
    "Castelnau-le-Lez",
    "Montpellier",
    "Le Crès",
    "Jacou",
    "Clapiers",
    "Vendargues",
    "Et partout en France en visioconférence"
  ],
  "nav": [
    { "label": "Accueil", "url": "/", "icon": "fa-house" },
    { "label": "Qui suis-je ?", "url": "/qui-suis-je/", "icon": "fa-paw" },
    { "label": "Prestations", "url": "/prestations/", "icon": "fa-list-check" },
    { "label": "Formation", "url": "/formation/", "icon": "fa-graduation-cap" },
    { "label": "FAQ", "url": "/faq/", "icon": "fa-circle-question" },
    { "label": "Contact", "url": "/contact/", "icon": "fa-envelope" }
  ],
  "footerNav": [
    { "label": "Mentions légales", "url": "/mentions-legales/" },
    { "label": "Politique en matière de cookies", "url": "/cookies/" },
    { "label": "Politique de confidentialité", "url": "/confidentialite/" },
    { "label": "Conditions d'utilisation", "url": "/conditions/" }
  ]
}
